simpler_flash/__init__.py
simpler_flash/activations.py
simpler_flash/block.py
simpler_flash/flashattention.py
simpler_flash/flashformer.py
simpler_flash/flashpickattention.py
simpler_flash/hyper_attention.py
simpler_flash/layer_norm.py
simpler_flash/mha.py
simpler_flash/mlp.py
simpler_flash/og_flashsoftpick.py
simpler_flash/hyper/__init__.py
simpler_flash/hyper/angular_lsh_triton.py
simpler_flash/hyper/attn_utils.py
simpler_flash/hyper/hyper_attn_triton.py
simpler_flash-1.2.0.dist-info/METADATA
simpler_flash-1.2.0.dist-info/WHEEL
simpler_flash-1.2.0.dist-info/licenses/LICENSE
simpler_flash-1.2.0.dist-info/RECORD
