Metadata-Version: 2.4
Name: simpler-flash
Version: 1.2.0
Summary: a simpler version of flashattention
Project-URL: Documentation, https://simpler_flash.readthedocs.io/
Project-URL: Homepage, https://github.com/jkobject/simpler_flash
Project-URL: Source, https://github.com/jkobject/simpler_flash
Author: jkobject
Maintainer-email: jkobject <jkobject@gmail.com>
License: MIT License
License-File: LICENSE
Classifier: Programming Language :: Python :: 3 :: Only
Classifier: Programming Language :: Python :: 3.10
Classifier: Programming Language :: Python :: 3.11
Classifier: Programming Language :: Python :: 3.12
Classifier: Programming Language :: Python :: 3.13
Requires-Python: >=3.10
Requires-Dist: einops>=0.6.1
Requires-Dist: performer-pytorch>=1
Requires-Dist: session-info
Requires-Dist: torch==2.2
Requires-Dist: torchaudio>=2.2
Requires-Dist: torchdata>=0.5
Requires-Dist: torchtext>=0.17
Requires-Dist: torchvision>=0.17
Provides-Extra: doc
Requires-Dist: docutils!=0.18.*,!=0.19.*,>=0.8; extra == 'doc'
Requires-Dist: ipykernel; extra == 'doc'
Requires-Dist: ipython; extra == 'doc'
Requires-Dist: myst-nb>=1.1; extra == 'doc'
Requires-Dist: pandas; extra == 'doc'
Requires-Dist: setuptools; extra == 'doc'
Requires-Dist: sphinx-autodoc-typehints; extra == 'doc'
Requires-Dist: sphinx-book-theme>=1; extra == 'doc'
Requires-Dist: sphinx-copybutton; extra == 'doc'
Requires-Dist: sphinx-tabs; extra == 'doc'
Requires-Dist: sphinx>=4; extra == 'doc'
Requires-Dist: sphinxcontrib-bibtex>=1; extra == 'doc'
Requires-Dist: sphinxext-opengraph; extra == 'doc'
